tests/__init__.py
tests/test.py
vconnex/__init__.py
vconnex/api.py
vconnex/device.py
vconnex.py-1.0.10.dist-info/LICENSE.txt
vconnex.py-1.0.10.dist-info/METADATA
vconnex.py-1.0.10.dist-info/WHEEL
vconnex.py-1.0.10.dist-info/top_level.txt
vconnex.py-1.0.10.dist-info/RECORD
