Metadata-Version: 2.1
Name: vconnex.py
Version: 1.0.10
Summary: A Python library for Vconnex Open API
Author: Vconnex Inc.
License: MIT
Keywords: vconnex python
Requires-Python: >=3.7
License-File: LICENSE.txt
Requires-Dist: requests
Requires-Dist: paho-mqtt
